setup.cfg
setup.py
RTool/__init__.py
RTool/attributeComparer.py
RTool/attributeComparerGUI.py
RTool/audio.py
RTool/image.py
RTool/time.py
RTool/video.py
RTool.egg-info/PKG-INFO
RTool.egg-info/SOURCES.txt
RTool.egg-info/dependency_links.txt
RTool.egg-info/top_level.txt
RTool/ffmpeg/__init__.py
RTool/ffmpeg/util.py
RTool/ffmpeg/bin/__init__.py
RTool/maya/OptionsWindowBaseClass.py
RTool/maya/SWE449.py
RTool/maya/__init__.py
RTool/maya/attributeComparerGUI.py
RTool/maya/audio.py
RTool/maya/util.py
RTool/prototype/__init__.py
RTool/prototype/tos.py
RTool/util/__init__.py
RTool/util/importer.py