Metadata-Version: 1.1
Name: RTool
Version: 0.0.2.3.7
Summary: A collection of personal tools, mostly Windows dependant
Home-page: https://github.com/RonNofar/RToolPackage
Author: Ron Nofar
Author-email: ronnofar2@gmail.com
License: UNKNOWN
Download-URL: https://github.com/RonNofar/RToolPackage/archive/0.0.2.3.7.tar.gz
Keywords: RTool,win32,Maya
Platform: UNKNOWN
